pymaths/constants/__init__.py
pymaths/constants/all.py
pymaths/constants/chemistry.py
pymaths/constants/maths.py
pymaths/constants/physics.py
pymaths/functions/__init__.py
pymaths/functions/calculus.py
pymaths/functions/pure.py
pymaths/functions/statistics.py
pymaths-1.4.dist-info/LICENSE.txt
pymaths-1.4.dist-info/METADATA
pymaths-1.4.dist-info/WHEEL
pymaths-1.4.dist-info/top_level.txt
pymaths-1.4.dist-info/RECORD
