Metadata-Version: 2.1
Name: pymaths
Version: 1.4
Summary: An advanced maths plugin for Python 3.
Home-page: https://matthew-byrne.co.uk
Author: Matthew Byrne
Author-email: matthewlukebyrne19@gmail.com
License: MIT
Platform: UNKNOWN
Requires: sympy
